{
  "cities": [
    {
      "cityName": "Lisbon",
      "country": "Portugal",
      "emoji": "🇵🇹",
      "date": "2027-10-31T15:59:59.138Z",
      "notes": "My favorite city so far!",
      "position": {
        "lat": 38.727881642324164,
        "lng": -9.140900099907554
      },
      "id": 73930385
    },
    {
      "cityName": "Madrid",
      "country": "Spain",
      "emoji": "🇪🇸",
      "date": "2027-07-15T08:22:53.976Z",
      "notes": "",
      "position": {
        "lat": 40.46635901755316,
        "lng": -3.7133789062500004
      },
      "id": 17806751
    },
    {
      "cityName": "Larvik",
      "country": "Norway",
      "emoji": "🇳🇴",
      "date": "2026-01-29T04:12:39.397Z",
      "notes": "had fun!!!",
      "position": {
        "lat": "59.445075099047166",
        "lng": "9.843750000000002"
      },
      "id": 73930386
    },
    {
      "cityName": "Vilanova de l'Aguda",
      "country": "Spain",
      "emoji": "🇪🇸",
      "date": "2026-01-29T04:14:45.805Z",
      "notes": "good place",
      "position": {
        "lat": "41.88592102814744",
        "lng": "1.2524414062500002"
      },
      "id": 73930387
    },
    {
      "cityName": "Surendranagar",
      "country": "India",
      "emoji": "🇮🇳",
      "date": "2026-01-29T04:15:12.275Z",
      "notes": "must visit!!!!",
      "position": {
        "lat": "22.755920681486405",
        "lng": "71.71875000000001"
      },
      "id": 73930388
    }
  ]
}